headerbreakdown.py
headerbreakdown-0.1.5.dist-info/LICENSE
headerbreakdown-0.1.5.dist-info/METADATA
headerbreakdown-0.1.5.dist-info/WHEEL
headerbreakdown-0.1.5.dist-info/top_level.txt
headerbreakdown-0.1.5.dist-info/RECORD
