Metadata-Version: 2.1
Name: headerbreakdown
Version: 0.1.5
Summary: converts a collection of HTTP headers into a dictionary structure for automated analysis; creates parsed and analyzed objects; accepts strings, lists, or dictionaries of header values
Home-page: https://github.com/bonifield/HeaderBreakdown
Author: James Bonifield
Author-email: bonifield.tools@gmail.com
License: UNKNOWN
Platform: UNKNOWN
Classifier: Programming Language :: Python :: 3
Classifier: License :: OSI Approved :: MIT License
Classifier: Operating System :: OS Independent
License-File: LICENSE
